Workbook

Sheet Fuentes
A1: Fuentes y supuestos — modelo de mercado de PYMEs en México
A2: Cambia cualquier celda de la columna Valor marcada como SUPUESTO — todo el modelo se recalcula solo.
A4: Variable | B4: Valor | C4: Tipo | D4: Fuente
A5: Universo total de unidades económicas privadas y paraestatales en México | B5: 5451113 | C5: DATO | D5: INEGI, Censos Económicos 2024 (resultados definitivos)
A6: % Microempresas (0–10 empleados) | B6: 0.954 | C6: DATO | D6: INEGI, Censos Económicos 2024
A7: % Pequeña empresa | B7: 0.037 | C7: DATO | D7: INEGI, Censos Económicos 2024
A8: % Mediana empresa | B8: 0.007 | C8: DATO | D8: INEGI, Censos Económicos 2024
A9: % Grande empresa | B9: 0.002 | C9: DATO | D9: INEGI, Censos Económicos 2024
A10: % unidades económicas en Comercio | B10: 0.467 | C10: DATO | D10: INEGI, Censos Económicos 2019 (desglose sectorial público más reciente localizado)
A11: % unidades económicas en Servicios | B11: 0.391 | C11: DATO | D11: INEGI, Censos Económicos 2019
A12: % unidades económicas en Manufactura | B12: 0.122 | C12: DATO | D12: INEGI, Censos Económicos 2019
A13: % Resto de actividades | B13: 0.02 | C13: DATO | D13: INEGI, Censos Económicos 2019
A14: Restaurantes en México (unidades económicas) | B14: 641000 | C14: DATO | D14: INEGI–CANIRAC, "Conociendo la Industria Restaurantera"
A15: % de restaurantes que son microempresas | B15: 0.96 | C15: DATO | D15: INEGI–CANIRAC
A16: % de restaurantes pequeña/mediana (derivado) | B16: =1-B15 -> 0.04 | C16: DATO (derivado) | D16: Calculado como 1 − % microempresas (fila anterior)
A17: Servicios profesionales, científicos y técnicos — SCIAN 54, todas las ramas (unidades económicas) | B17: 109630 | C17: DATO | D17: DENUE 2025
A18: Unidades SCIAN 54 en Estado de México | B18: 11373 | C18: DATO | D18: DENUE 2025
A19: Unidades SCIAN 54 en Ciudad de México | B19: 11058 | C19: DATO | D19: DENUE 2025
A20: Universo encuestado ENAPROCE 2018 (empresas) | B20: 4182049 | C20: DATO | D20: INEGI / Secretaría de Economía, ENAPROCE 2018
A21: % que usa contador o paquetería contable | B21: 0.577 | C21: DATO | D21: ENAPROCE 2018
A22: % que no lleva ninguna contabilidad | B22: 0.181 | C22: DATO | D22: ENAPROCE 2018
A23: % de PyMEs en México que usan tecnologías de la información | B23: 0.059 | C23: DATO | D23: El Financiero, citando estudio de adopción tecnológica en PyMEs
A24: % de mipymes con herramientas digitales que usan algún ERP | B24: 0.14 | C24: DATO | D24: Radiografía del Emprendimiento en México 2021
A26: SUPUESTOS EDITABLES — cambia estos valores para recalcular todo el modelo
A27: % del sector de servicios profesionales que califica por tamaño/facturación suficiente (Vía A) | B27: 0.25 | C27: SUPUESTO | D27: Estimación editable — la estratificación censal por número de empleados subestima despachos boutique con pocos empleados pero facturación de pequeña empresa
A28: % que hoy opera de forma artesanal / sin sistema real (Vía A y Vía B) | B28: 0.85 | C28: SUPUESTO | D28: Estimación editable, informada por la baja adopción de TI/ERP citada arriba (filas 23–24) — no es un dato censal directo
A29: % direccionable en el corto plazo (Vía A y Vía B) | B29: 0.2 | C29: SUPUESTO | D29: Estimación editable — presencia digital mínima, zona geográfica prospectable, disposición a invertir en consultoría
A31: Leyenda: texto azul = dato/insumo fijo tomado de la fuente citada. Relleno amarillo + texto azul = SUPUESTO editable (cámbialo aquí; el resto del modelo usa esta misma celda). Texto negro = resultado calculado con fórmula.
A33: Datos adicionales — banda legal de ingresos anuales por tamaño de empresa
A34: Piso de ingresos anuales — Pequeña empresa (millones de pesos) | B34: 4.01 | C34: DATO | D34: Estratificación oficial MIPYME (Ley para el Desarrollo de la Competitividad de la MIPYME / Acuerdo DOF)
A35: Techo de Pequeña empresa / piso de Mediana empresa (millones de pesos) | B35: 100 | C35: DATO | D35: Estratificación oficial MIPYME (Ley para el Desarrollo de la Competitividad de la MIPYME / Acuerdo DOF)
A36: Techo de Mediana empresa (millones de pesos) | B36: 250 | C36: DATO | D36: Estratificación oficial MIPYME (Ley para el Desarrollo de la Competitividad de la MIPYME / Acuerdo DOF)

Sheet Via A
A1: Vía A — Servicios que cotizan proyecto por proyecto (diseño, consultoría, arquitectura, construcción)
A2: Todas las celdas de esta hoja son fórmulas que jalan de 'Fuentes' — para cambiar un supuesto, edítalo allá.
A4: Paso | B4: Descripción | C4: Valor | D4: Notas
A5: 1 | B5: Unidades económicas en SCIAN 54 (servicios profesionales, científicos y técnicos: legal, contable, arquitectura, ingeniería, diseño especializado, TI, consultoría, publicidad, etc.) | C5: =Fuentes!$B$17 -> 109630 | D5: Enlace a 'Fuentes' (dato oficial)
A6: 2 | B6: % que tiene tamaño/facturación suficiente para justificar el servicio (no es una sola persona de subsistencia) | C6: =Fuentes!$B$27 -> 0.25 | D6: Enlace a 'Fuentes'
B7: Subtotal tras filtro de tamaño/facturación | C7: =C5*C6 -> 27407.5
A8: 3 | B8: % que hoy opera de forma artesanal / sin sistema real | C8: =Fuentes!$B$28 -> 0.85 | D8: Enlace a 'Fuentes' (supuesto compartido con la otra vía)
B9: Subtotal tras filtro de necesidad (sin sistema real) | C9: =C7*C8 -> 23296.375
A10: 4 | B10: % direccionable en el corto plazo | C10: =Fuentes!$B$29 -> 0.2 | D10: Enlace a 'Fuentes' (supuesto compartido con la otra vía)
B11: MERCADO OBTENIBLE SERVIBLE (SOM) — VÍA A | C11: =C9*C10 -> 4659.275

Sheet Via B
A1: Vía B — Operación diaria multicanal (restaurantes como ancla del segmento; extensible a retail)
A2: Todas las celdas de esta hoja son fórmulas que jalan de 'Fuentes' — para cambiar un supuesto, edítalo allá.
A4: Paso | B4: Descripción | C4: Valor | D4: Notas
A5: 1 | B5: Restaurantes en México (unidades económicas) | C5: =Fuentes!$B$14 -> 641000 | D5: Enlace a 'Fuentes' (dato oficial)
A6: 2 | B6: % pequeña/mediana (excluye el 96% que son microempresas de subsistencia) | C6: =Fuentes!$B$16 -> 0.04 | D6: Enlace a 'Fuentes'
B7: Subtotal tras filtro de tamaño/facturación | C7: =C5*C6 -> 25640
A8: 3 | B8: % que hoy opera de forma artesanal / sin sistema real | C8: =Fuentes!$B$28 -> 0.85 | D8: Enlace a 'Fuentes' (supuesto compartido con la otra vía)
B9: Subtotal tras filtro de necesidad (sin sistema real) | C9: =C7*C8 -> 21794
A10: 4 | B10: % direccionable en el corto plazo | C10: =Fuentes!$B$29 -> 0.2 | D10: Enlace a 'Fuentes' (supuesto compartido con la otra vía)
B11: MERCADO OBTENIBLE SERVIBLE (SOM) — VÍA B | C11: =C9*C10 -> 4358.8

Sheet Resumen
A1: Resumen — mercado obtenible y capacidad real de atención
A2: Suma las dos vías y traduce el mercado obtenible en una meta operativa realista para un consultor independiente.
A4: Mercado obtenible servible (SOM) por vía
A5: SOM Vía A — servicios de proyecto | B5: ='Via A'!C11 -> 4659.275
A6: SOM Vía B — operación diaria multicanal | B6: ='Via B'!C11 -> 4358.8
A7: MERCADO OBTENIBLE SERVIBLE (SOM) TOTAL | B7: =B5+B6 -> 9018.075
A9: ¿Qué fracción del mercado necesitas capturar?
A10: Clientes objetivo | B10: % del SOM total
A11: 10 | B11: =A11/$B$7 -> 0.0011088841
A12: 25 | B12: =A12/$B$7 -> 0.0027722103
A13: 50 | B13: =A13/$B$7 -> 0.0055444205
A14: 100 | B14: =A14/$B$7 -> 0.011088841
A16: Capacidad real como consultor independiente
A17: Clientes nuevos instalados por trimestre (supuesto) | B17: 1.5
A18: Tasa de cancelación anual de cartera en monitoreo (supuesto) | B18: 0.1
A19: Techo de cartera en monitoreo simultáneo antes de necesitar contratar (supuesto) | B19: 18
A21: Año | B21: Nuevos clientes instalados | C21: Cartera al inicio del año | D21: Cartera en monitoreo al cierre
A22: Año 1 | B22: =$B$17*4 -> 6 | C22: 0 | D22: =MIN($B$19, C22*(1-$B$18)+B22) -> 6
A23: Año 2 | B23: =$B$17*4 -> 6 | C23: =D22 -> 6 | D23: =MIN($B$19, C23*(1-$B$18)+B23) -> 11.4
A24: Año 3 | B24: =$B$17*4 -> 6 | C24: =D23 -> 11.4 | D24: =MIN($B$19, C24*(1-$B$18)+B24) -> 16.26
A26: Foco geográfico sugerido
A27: % de SCIAN 54 nacional concentrado en CDMX + Estado de México | B27: =(Fuentes!$B$18+Fuentes!$B$19)/Fuentes!$B$17 -> 0.2046064
A28: Prospectar primero en Ciudad de México y Estado de México reduce fricción logística: concentran cerca de una quinta parte de los servicios profesionales del país. No hay un dato equivalente citado aquí para la concentración geográfica de restaurantes (Vía B).
A30: ¿Cuántos pueden pagar el ticket propuesto ($100,000 setup + $30,000/mes)?
A31: Setup propuesto (MXN) | B31: 100000
A32: Mensualidad propuesta (MXN) | B32: 30000
A33: Costo total año 1 (setup + 12 meses de mensualidad) | B33: =B31+B32*12 -> 460000
A34: Costo anual recurrente (año 2 en adelante) | B34: =B32*12 -> 360000
A36: % de ingresos anuales que representa un gasto "cómodo" — no una carga desproporcionada (umbral, supuesto) | B36: 0.08
A37: Ingreso anual mínimo para que el costo del año 1 sea ≤ umbral | B37: =B33/B36 -> 5750000
A38: Ingreso anual mínimo para sostener el costo recurrente ≤ umbral | B38: =B34/B36 -> 4500000
A39: Referencia — banda legal de ingresos anuales: Pequeña empresa $4.01–100 millones de pesos/año; Mediana empresa $100.01–250 millones de pesos/año (ver hoja 'Fuentes'). El ingreso mínimo recurrente calculado arriba cae dentro del tramo bajo de 'Pequeña' — es decir, una parte real pero no total de las empresas ya filtradas como Pequeña/Mediana puede sostenerlo sin que sea una carga desproporcionada.
A41: % del mercado obtenible (SOM) que se estima tiene ingresos suficientes para pagar este ticket cómodamente (supuesto) | B41: 0.35
A42: MERCADO QUE PUEDE PAGAR EL TICKET PROPUESTO | B42: =B7*B41 -> 3156.3263
A43: Nota: el 35% es la cifra menos sólida de todo el modelo — no encontré una distribución pública de ingresos DENTRO de la banda Pequeña/Mediana en México (esa banda va de $4M a $250M/año, un rango enorme). Es una estimación de sentido común, no un dato censal. El punto de referencia más confiable que existe es tu cliente actual: compara qué % de sus ingresos representa lo que le cobras hoy, y ajusta esta celda con ese punto de anclaje real.

Sheet Sensibilidad
A1: Sensibilidad — 3 escenarios
A2: La columna Base jala en vivo de 'Fuentes'; Conservador y Optimista son palancas de escenario independientes (edítalas aquí).
A4: Variable | B4: Conservador | C4: Base | D4: Optimista
A5: % califica por tamaño/facturación (Vía A) | B5: 0.15 | C5: =Fuentes!$B$27 -> 0.25 | D5: 0.35
A6: % que opera de forma artesanal / sin sistema real | B6: 0.75 | C6: =Fuentes!$B$28 -> 0.85 | D6: 0.9
A7: % direccionable en el corto plazo | B7: 0.1 | C7: =Fuentes!$B$29 -> 0.2 | D7: 0.3
A9: SOM Vía A resultante | B9: =Fuentes!$B$17*B5*B6*B7 -> 1233.3375 | C9: =Fuentes!$B$17*C5*C6*C7 -> 4659.275 | D9: =Fuentes!$B$17*D5*D6*D7 -> 10360.035
A10: SOM Vía B resultante | B10: =Fuentes!$B$14*Fuentes!$B$16*B6*B7 -> 1923 | C10: =Fuentes!$B$14*Fuentes!$B$16*C6*C7 -> 4358.8 | D10: =Fuentes!$B$14*Fuentes!$B$16*D6*D7 -> 6922.8
A11: SOM TOTAL | B11: =B9+B10 -> 3156.3375 | C11: =C9+C10 -> 9018.075 | D11: =D9+D10 -> 17282.835

Sheet Valoracion
A1: Valoración — proyección de ingresos y rango de valor del negocio
A2: Ilustrativo, NO es una valoración formal: no incorpora margen real, estructura de costos ni contratos. Útil para ver el orden de magnitud, no para negociar una venta. El techo aquí es tu capacidad operativa (hoja 'Resumen'), no el tamaño de mercado — el mercado ya es muchas veces mayor que lo que puedes atender solo.
A4: Proyección de ingresos (usa la capacidad operativa ya modelada en 'Resumen')
A5: Año | B5: Nuevos clientes instalados | C5: Cartera al inicio del año | D5: Cartera al cierre del año | E5: Ingreso por setup (MXN) | F5: Ingreso recurrente promedio del año (MXN) | G5: Ingreso total del año (MXN)
A6: =Resumen!A22 -> Año 1 | B6: =Resumen!B22 -> 6 | C6: =Resumen!C22 -> 0 | D6: =Resumen!D22 -> 6 | E6: =B6*Resumen!$B$31 -> 600000 | F6: =AVERAGE(C6,D6)*Resumen!$B$32*12 -> 1080000 | G6: =E6+F6 -> 1680000
A7: =Resumen!A23 -> Año 2 | B7: =Resumen!B23 -> 6 | C7: =Resumen!C23 -> 6 | D7: =Resumen!D23 -> 11.4 | E7: =B7*Resumen!$B$31 -> 600000 | F7: =AVERAGE(C7,D7)*Resumen!$B$32*12 -> 3132000 | G7: =E7+F7 -> 3732000
A8: =Resumen!A24 -> Año 3 | B8: =Resumen!B24 -> 6 | C8: =Resumen!C24 -> 11.4 | D8: =Resumen!D24 -> 16.26 | E8: =B8*Resumen!$B$31 -> 600000 | F8: =AVERAGE(C8,D8)*Resumen!$B$32*12 -> 4978800 | G8: =E8+F8 -> 5578800
A10: Ingreso recurrente anualizado de salida (ARR) al cierre del Año 3 | B10: =Resumen!D24*Resumen!$B$32*12 -> 5853600
A12: Múltiplos de valoración (supuestos)
A13: Negocio de servicios boutique, un solo operador, alto riesgo de dependencia de una persona clave (si tú no estás, ¿el negocio sigue?). No es una empresa de software (TINO no es tuyo, la automatización es a la medida) — no apliques múltiplos de SaaS (5–10x ARR). Rangos típicos para consultoría boutique de una persona: 0.5x–1.5x del ingreso recurrente anualizado.
A14: Escenario | B14: Múltiplo sobre ARR | C14: Valor estimado (MXN)
A15: Conservador | B15: 0.5 | C15: =$B$10*B15 -> 2926800
A16: Base | B16: 1 | C16: =$B$10*B16 -> 5853600
A17: Optimista | B17: 1.5 | C17: =$B$10*B17 -> 8780400
A19: Nota: hoy tienes un cliente real operando — no una cartera de varios clientes con historial. Este rango es hacia dónde apunta el negocio si la proyección de capacidad se cumple, no lo que vale hoy. Lo que más sube el múltiplo real, si algún día quieres vender o atraer socios: que el sistema funcione sin que tú estés en cada cuenta (documentación, un segundo operador, procesos repetibles), y contratos de monitoreo firmados a 12+ meses en vez de mes a mes.

Sheet Escala30M
A1: ¿Es factible escalar a $30M MXN/año?
A2: Este modelo sólo proyecta ingreso, no utilidad: no incluye sueldos de los operadores nuevos, costo de adquisición de clientes, ni gastos de operación. Responde '¿el ingreso es alcanzable?', no '¿es un buen negocio a esa escala?'.
A4: Objetivo de ingreso anual (MXN) | B4: 30000000
A5: Cartera en monitoreo necesaria (asumiendo que el ingreso viene sobre todo de mensualidades) | B5: =B4/(Resumen!$B$32*12) -> 83.333333
A6: Operadores equivalentes necesarios (usando tu propio techo por operador de 'Resumen') | B6: =ROUNDUP(B5/Resumen!$B$19,0) -> 5
A7: Clientes nuevos por año que hacen falta sólo para reponer bajas en estado estable (cartera × tasa de cancelación) | B7: =B5*Resumen!$B$18 -> 8.3333333
A9: Trayectoria — ¿cuánto tarda en llegar, contratando ~1 operador nuevo por año?
A10: 'Operadores activos' es un supuesto editable por año (empieza en ti solo). Cada operador aporta la misma capacidad que la tuya en 'Resumen': 1.5 clientes nuevos instalados por trimestre, techo de 18 en cartera. Es una simplificación — en la práctica un operador nuevo tarda en llegar a ese ritmo.
A11: Año | B11: Operadores activos (supuesto) | C11: Nuevos clientes instalados | D11: Techo de cartera | E11: Cartera al inicio | F11: Cartera al cierre | G11: Ingreso recurrente del año (MXN) | H11: Ingreso por setups (MXN) | I11: Ingreso total del año (MXN)
A12: Año 1 | B12: 1 | C12: =B12*Resumen!$B$17*4 -> 6 | D12: =B12*Resumen!$B$19 -> 18 | E12: 0 | F12: =MIN(D12, E12*(1-Resumen!$B$18)+C12) -> 6 | G12: =AVERAGE(E12,F12)*Resumen!$B$32*12 -> 1080000 | H12: =C12*Resumen!$B$31 -> 600000 | I12: =G12+H12 -> 1680000
A13: Año 2 | B13: 2 | C13: =B13*Resumen!$B$17*4 -> 12 | D13: =B13*Resumen!$B$19 -> 36 | E13: =F12 -> 6 | F13: =MIN(D13, E13*(1-Resumen!$B$18)+C13) -> 17.4 | G13: =AVERAGE(E13,F13)*Resumen!$B$32*12 -> 4212000 | H13: =C13*Resumen!$B$31 -> 1200000 | I13: =G13+H13 -> 5412000
A14: Año 3 | B14: 3 | C14: =B14*Resumen!$B$17*4 -> 18 | D14: =B14*Resumen!$B$19 -> 54 | E14: =F13 -> 17.4 | F14: =MIN(D14, E14*(1-Resumen!$B$18)+C14) -> 33.66 | G14: =AVERAGE(E14,F14)*Resumen!$B$32*12 -> 9190800 | H14: =C14*Resumen!$B$31 -> 1800000 | I14: =G14+H14 -> 10990800
A15: Año 4 | B15: 4 | C15: =B15*Resumen!$B$17*4 -> 24 | D15: =B15*Resumen!$B$19 -> 72 | E15: =F14 -> 33.66 | F15: =MIN(D15, E15*(1-Resumen!$B$18)+C15) -> 54.294 | G15: =AVERAGE(E15,F15)*Resumen!$B$32*12 -> 15831720 | H15: =C15*Resumen!$B$31 -> 2400000 | I15: =G15+H15 -> 18231720
A16: Año 5 | B16: 5 | C16: =B16*Resumen!$B$17*4 -> 30 | D16: =B16*Resumen!$B$19 -> 90 | E16: =F15 -> 54.294 | F16: =MIN(D16, E16*(1-Resumen!$B$18)+C16) -> 78.8646 | G16: =AVERAGE(E16,F16)*Resumen!$B$32*12 -> 23968548 | H16: =C16*Resumen!$B$31 -> 3000000 | I16: =G16+H16 -> 26968548
A17: Año 6 | B17: 6 | C17: =B17*Resumen!$B$17*4 -> 36 | D17: =B17*Resumen!$B$19 -> 108 | E17: =F16 -> 78.8646 | F17: =MIN(D17, E17*(1-Resumen!$B$18)+C17) -> 106.97814 | G17: =AVERAGE(E17,F17)*Resumen!$B$32*12 -> 33451693 | H17: =C17*Resumen!$B$31 -> 3600000 | I17: =G17+H17 -> 37051693
A19: Nota: la meta de mercado no es el cuello de botella — necesitas ~80-100 clientes activos de un mercado obtenible de ~9,000 (hoja 'Resumen'). El cuello de botella real es operativo: pasar de consultor solo a un equipo de 5-6 personas sin perder la calidad que hace verificable el trabajo (auditoría v1/v2), y el ritmo de ventas necesario para llenar esa capacidad nueva cada año. Este modelo no dice si la economía por operador (sueldo vs. ingreso que genera) funciona — sólo que el ingreso agregado es alcanzable.
